.gitignore
AUTHORS
LICENSE
NOTICE
README.rst
setup.py
flint/__init__.py
flint/calls.py
flint/cli.py
flint/construct.py
flint/document.py
flint/ftoken.py
flint/interface.py
flint/intrinsics.py
flint/lexer.py
flint/lines.py
flint/project.py
flint/scanner.py
flint/source.py
flint/statement.py
flint/syntax.py
flint/variable.py
flint.egg-info/PKG-INFO
flint.egg-info/SOURCES.txt
flint.egg-info/dependency_links.txt
flint.egg-info/entry_points.txt
flint.egg-info/top_level.txt
flint/tools/__init__.py
flint/tools/format.py
flint/tools/gendoc.py
flint/tools/report.py
flint/tools/tag.py
flint/units/__init__.py
flint/units/function.py
flint/units/module.py
flint/units/program.py
flint/units/submodule.py
flint/units/subroutine.py
flint/units/unit.py
test/test_scanner.py
test/test_tokenize.py