Metadata-Version: 2.1
Name: flint
Version: 0.0.1
Summary: Fortran code analysis tool
Home-page: http://github.com/marshallward/flint
Author: Marshall Ward
Author-email: flint@marshallward.org
License: UNKNOWN
Platform: UNKNOWN
Classifier: Development Status :: 1 - Planning
Classifier: Programming Language :: Python :: 3.9
Classifier: Topic :: Utilities
License-File: LICENSE
License-File: NOTICE
License-File: AUTHORS
